[
  {
    "label": "layout.navFactory",
    "icon": "/img/Home-Icon.svg",
    "to": {
      "path": "factory"
    },
    "isSuperAdminApp": true
  },
  {
    "label": "layout.navOverview",
    "icon": "/img/icon-overview.svg",
    "inFactory": true,
    "to": {
      "path": "overview"
    }
  },
  {
    "label": "layout.navSensor",
    "icon": "/img/sensor.svg",
    "inFactory": true,
    "to": {
      "path": "sensor"
    }
  },
  {
    "label": "layout.navDevice",
    "icon": "/img/device.svg",
    "inFactory": true,
    "to": {
      "path": "device"
    }
  },
  {
    "label": "layout.navChart",
    "icon": "/img/bar-chart.svg",
    "inFactory": true,
    "to": {
      "path": "chart"
    }
  },
  {
    "label": "layout.navMaps",
    "icon": "/img/place.svg",
    "inFactory": true,
    "to": {
      "path": "maps"
    }
  },
  {
    "label": "layout.navSetting",
    "icon": "/img/settings.svg",
    "to": {
      "path": "setting"
    },
    "isSuperAdminApp": true
  }
]
